<?xml version="1.0" encoding="UTF-8"?><bible><text chap="1"><div class='document bible' dir='ltr'><div id='p1' class='par'><p class='sb'><span id='dcv_1_1' class='dc'>1 </span>オバデヤの幻:</p></div><div id='p2' class='par'><p class='sb'>これは<u>主権者なる主</u>エホバがエドムに関して言われたことである<a class='mr'></a>。「わたしたちがエホバから聞いた知らせがある。諸国民の中に遣わされた使節がいる。『あなた方は立ち上がれ。彼女に対する戦闘に立ち上がろう<a class='mr'></a>』」。</p></div><div id='p3' class='par'><p class='sb'><span id='dcv_1_2' class='dv'>2 </span>「見よ，わたしはあなたを諸国民の中の小さな者とした<a class='mr'></a>。あなたは大いにさげすまれている<a class='mr'></a>。<span id='dcv_1_3' class='dv'>3 </span>あなたの心のせん越さがあなたを欺いた<a class='mr'></a>。大岩の隠れ場に，自分の住まう高みにとどまっている者<a class='fn'></a><a class='mr'></a>，その心に，『だれがわたしを地に引き下ろすだろうか』と言う者よ。<span id='dcv_1_4' class='dv dx'><a>4 </a></span>たとえあなたが自分の居所を鷲のように高くしようとも，また星の間に巣をかけようとも，わたしはそこからあなたを引き下ろす<a class='mr'></a>」と，エホバはお告げになる。</p></div><div id='p4' class='par'><p class='sb'><span id='dcv_1_5' class='dv dx'><a>5 </a></span>「あなたのところに来たのが盗人であったなら，奪い取る者が夜の間に[入って来た]のであれば，あなたはどれほど<a class='fn'></a>沈黙したであろうか<a class='mr'></a>。彼らは自分の望むだけのものを盗むのではないか。また，あなたのところに来たのがぶどうを集める者であったなら，多少の採り残しを残しておかないだろうか<a class='mr'></a>。<span id='dcv_1_6' class='dv dx'><a>6 </a></span>だが，エサウに属する者たちはどこまで<a class='fn'></a>調べ出されたことか<a class='mr'></a>。その秘められた宝は[いかに]探り出されたことか。<span id='dcv_1_7' class='dv dx'><a>7 </a></span>彼らは境界にまであなたを追いやった。あなたと契約を結んでいた者たち<a class='fn'></a>が皆あなたを欺いた<a class='mr'></a>。あなたと平和に過ごしていた者たちがあなたを打ち負かした<a class='mr'></a>。あなたと食物を共にしていた者たち<a class='fn'></a>が，識別力のない者<a class='mr'></a>のようにしてあなたの下に網を敷くであろう。<span id='dcv_1_8' class='dv'>8 </span>その日にはそのようになるのではないか」と，エホバはお告げになる。</p></div><div id='p5' class='par'><p class='sb'>「そしてわたしはエドムから必ず賢者を滅ぼし去り<a class='mr'></a>，エサウの山地から識別力を[尽きさせる]。<span id='dcv_1_9' class='dv'>9 </span>また，テマンよ<a class='mr'></a>，あなたの力ある者たちは恐れおののくことになる<a class='mr'></a>。殺りく<a class='mr'></a>のため，一人一人<a class='fn'></a>エサウの山地から断たれるからである<a class='mr'></a>。<span id='dcv_1_10' class='dv dx'><a>10 </a></span>あなたの兄弟ヤコブに対する暴虐のゆえに<a class='mr'></a>恥辱があなたを覆う<a class='mr'></a>。あなたは定めのない時に至るまで切り断たれることになる<a class='mr'></a>。<span id='dcv_1_11' class='dv'>11 </span>あなたが離れてわきに立った日，よそ人たちが彼の軍勢をとりこにし<a class='mr'></a>，全くの異国人が彼の門をくぐり<a class='mr'></a>，エルサレムに関してくじを引いた日<a class='mr'></a>，あなたもまたその一人のようであった。</p></div><div id='p6' class='par'><p class='sb'><span id='dcv_1_12' class='dv dx'><a>12 </a></span>「またあなたは，あなたの兄弟の日，その不運の日に，その光景を見守っているべきではない<a class='mr'></a>。ユダの子らが滅びの日にあるのを見て歓ぶべきではない<a class='mr'></a>。[彼らの]苦難の日に大口を開けているべきではない。<span id='dcv_1_13' class='dv'>13 </span>わたしの民の災難の日にその門の中へ入って来るべきではない<a class='mr'></a>。あなたは彼の災難の日にその災いを見つめるべきではない。彼の災難の日にその富に手を出すべきではない<a class='fn'></a><a class='mr'></a>。<span id='dcv_1_14' class='dv'>14 </span>また，道の分かれる所に立って，逃れて来た者たちを断ち滅ぼそうとすべきではない<a class='mr'></a>。災難の日にその生き残った者たちを引き渡すべきでもない<a class='mr'></a>。<span id='dcv_1_15' class='dv'>15 </span>あらゆる国の民に対するエホバの日が近い<a class='fn'></a>からである<a class='mr'></a>。あなたがしたとおりにあなたに対しても行なわれる<a class='mr'></a>。あなたの加えた仕打ちがあなた自身の頭に帰する<a class='mr'></a>。<span id='dcv_1_16' class='dv'>16 </span>あなた方がわたしの聖なる山で飲んだとおりに，すべての国の民も常にそのようにして飲みつづけるのである<a class='mr'></a>。そして彼らはまさに飲んで飲み干し，まるでいなかったかのようになる。</p></div><div id='p7' class='par'><p class='sb'><span id='dcv_1_17' class='dv dx'><a>17 </a></span>「だが，シオンの山には逃れて来る者たちがいるであろう<a class='mr'></a>。そこは必ず聖なる所とされるのである<a class='mr'></a>。そしてヤコブの家はその取得すべき物を取得しなければならない<a class='fn'></a><a class='mr'></a>。<span id='dcv_1_18' class='dv dx'><a>18 </a></span>また，ヤコブの家は火となり<a class='mr'></a>，ヨセフの家は炎とならねばならない。そしてエサウの家は刈り株と[なるのである<a class='mr'></a>]。それを燃え立たせ，むさぼり食うのである。こうしてエサウの家には生き残る者がいなくなる<a class='mr'></a>。エホバ自ら[これを]語ったのである。<span id='dcv_1_19' class='dv'>19 </span>そして彼らはネゲブ<a class='fn'></a>を，まさにエサウの山地に属する所を<a class='mr'></a>，またシェフェラ<a class='fn'></a>を，すなわちフィリスティア人<a class='mr'></a>に属する所を取得しなければならない。さらに彼らはエフライム<a class='mr'></a>の野とサマリア<a class='mr'></a>の野を取得しなければならない。そしてベニヤミンはギレアデ<a class='mr'></a>を[取得するように]。<span id='dcv_1_20' class='dv dx'><a>20 </a></span>また，この塁壁<a class='fn'></a><a class='mr'></a>の流刑者たちについても，カナン人<a class='mr'></a>の[所有していた]所はザレパテ<a class='mr'></a>に至るまでイスラエルの子らのものとなる。そして，エルサレムの流刑者，セファラドにいた者たちは，ネゲブの諸都市<a class='mr'></a>を取得する。</p></div><div id='p8' class='par'><p class='sb'><span id='dcv_1_21' class='dv dx'><a>21 </a></span>「そして，救う者たち<a class='fn'></a><a class='mr'></a>は必ずシオンの山に<a class='fn'></a>上って来る<a class='mr'></a>。エサウの山地を裁くためである<a class='mr'></a>。こうして王権はエホバのものとされなければならない<a class='mr'></a>」。</p></div></div></text>
</bible>
