<?xml version="1.0" encoding="UTF-8"?><bible><text chap="1"><div class='document bible' dir='ltr'><div id='p1' class='par'><p class='sb'><span id='dcv_1_1' class='dc dx dp'><a>1 </a></span>The words of A′mos,<a class='fn'></a> who was among the sheep raisers from Te·ko′a,<a class='mr'></a> which he received in vision concerning Israel in the days of King Uz·zi′ah<a class='mr'></a> of Judah and in the days of Jer·o·bo′am<a class='mr'></a> son of Jo′ash,<a class='mr'></a> the king of Israel, two years before the earthquake.<a class='mr'></a> <span id='dcv_1_2' class='dv dp'><a>2 </a></span>He said:</p></div><div id='p2' class='par'><p class='sz'>“Jehovah will roar out of Zion,</p><p class='sz'><span class='br'></span>And he will raise his voice out of Jerusalem.</p></div><div id='p3' class='par'><p class='sz'>The pastures of the shepherds will mourn,</p><p class='sz'><span class='br'></span>And the summit of Car′mel will dry up.”<a class='mr'></a></p></div><div id='p4' class='par'><p class='sl'> <span id='dcv_1_3' class='dv dx dp'><a>3 </a></span>“This is what Jehovah says,</p><p class='sz'><span class='br'></span>‘“For three revolts<a class='fn'></a> of Damascus, and for four, I will not reverse it,</p><p class='sz'><span class='br'></span>Because they threshed Gil′e·ad with iron threshing sledges.<a class='mr'></a></p></div><div id='p5' class='par'><p class='sl'> <span id='dcv_1_4' class='dv dx dp'><a>4 </a></span>So I will send a fire upon the house of Haz′a·el,<a class='mr'></a></p><p class='sz'><span class='br'></span>And it will consume the fortified towers of Ben-ha′dad.<a class='mr'></a></p></div><div id='p6' class='par'><p class='sl'> <span id='dcv_1_5' class='dv dx dp'><a>5 </a></span>I will break the bars of Damascus;<a class='mr'></a></p><p class='sz'><span class='br'></span>I will destroy the inhabitants from Bik′ath-a′ven</p><p class='sz'><span class='br'></span>And the one ruling<a class='fn'></a> from Beth-e′den;</p><p class='sz'><span class='br'></span>And the people of Syria will go as exiles to Kir,”<a class='mr'></a> says Jehovah.’</p></div><div id='p7' class='par'><p class='sl'> <span id='dcv_1_6' class='dv dx dp'><a>6 </a></span>This is what Jehovah says,</p><p class='sz'><span class='br'></span>‘“For three revolts of Gaz′a,<a class='mr'></a> and for four, I will not reverse it,</p><p class='sz'><span class='br'></span>Because they took a whole group of exiles<a class='mr'></a> to hand them over to E′dom.</p></div><div id='p8' class='par'><p class='sl'> <span id='dcv_1_7' class='dv dp'><a>7 </a></span>So I will send a fire onto the wall of Gaz′a,<a class='mr'></a></p><p class='sz'><span class='br'></span>And it will consume her fortified towers.</p></div><div id='p9' class='par'><p class='sl'> <span id='dcv_1_8' class='dv dx dp'><a>8 </a></span>I will destroy the inhabitants from Ash′dod,<a class='mr'></a></p><p class='sz'><span class='br'></span>And the one ruling<a class='fn'></a> from Ash′ke·lon;<a class='mr'></a></p><p class='sz'><span class='br'></span>I will turn my hand against Ek′ron,<a class='mr'></a></p><p class='sz'><span class='br'></span>And the remaining Phi·lis′tines will perish,”<a class='mr'></a> says the Sovereign Lord Jehovah.’</p></div><div id='p10' class='par'><p class='sl'> <span id='dcv_1_9' class='dv dx dp'><a>9 </a></span>This is what Jehovah says,</p><p class='sz'><span class='br'></span>‘For three revolts of Tyre,<a class='mr'></a> and for four, I will not reverse it,</p><p class='sz'><span class='br'></span>Because they handed over a whole group of exiles to E′dom,</p><p class='sz'><span class='br'></span>And because they did not remember the covenant of brothers.<a class='mr'></a></p></div><div id='p11' class='par'><p class='sl'><span id='dcv_1_10' class='dv dp'><a>10 </a></span>So I will send a fire onto the wall of Tyre,</p><p class='sz'><span class='br'></span>And it will consume her fortified towers.’<a class='mr'></a></p></div><div id='p12' class='par'><p class='sl'><span id='dcv_1_11' class='dv dp'><a>11 </a></span>This is what Jehovah says,</p><p class='sz'><span class='br'></span>‘For three revolts of E′dom,<a class='mr'></a> and for four, I will not reverse it,</p><p class='sz'><span class='br'></span>Because he pursued his own brother with the sword,<a class='mr'></a></p><p class='sz'><span class='br'></span>And because he refused to show mercy;</p><p class='sz'><span class='br'></span>In his anger he keeps tearing them apart relentlessly,</p><p class='sz'><span class='br'></span>And he remains furious with them continually.<a class='mr'></a></p></div><div id='p13' class='par'><p class='sl'><span id='dcv_1_12' class='dv dp'><a>12 </a></span>So I will send a fire into Te′man,<a class='mr'></a></p><p class='sz'><span class='br'></span>And it will consume the fortified towers of Boz′rah.’<a class='mr'></a></p></div><div id='p14' class='par'><p class='sl'><span id='dcv_1_13' class='dv dp'><a>13 </a></span>This is what Jehovah says,</p><p class='sz'><span class='br'></span>‘“For three revolts of the Am′mon·ites,<a class='mr'></a> and for four, I will not reverse it,</p><p class='sz'><span class='br'></span>Because they ripped open the pregnant women of Gil′e·ad to widen out their own territory.<a class='mr'></a></p></div><div id='p15' class='par'><p class='sl'><span id='dcv_1_14' class='dv dp'><a>14 </a></span>So I will set fire to the wall of Rab′bah,<a class='mr'></a></p><p class='sz'><span class='br'></span>And it will consume her fortified towers,</p><p class='sz'><span class='br'></span>With a war cry in the day of battle,</p><p class='sz'><span class='br'></span>With a tempest in the day of storm wind.</p></div><div id='p16' class='par'><p class='sl'><span id='dcv_1_15' class='dv dp'><a>15 </a></span>And their king will go into exile together with his princes,”<a class='mr'></a> says Jehovah.’</p></div></div></text>
<text chap="2"><div class='document bible' dir='ltr'><div id='p17' class='par'><p class='sl'><span id='dcv_2_1' class='dc dx dp'><a>2 </a></span>“This is what Jehovah says,</p><p class='sl'><span class='br'></span>‘“For three revolts<a class='fn'></a> of Mo′ab,<a class='mr'></a> and for four, I will not reverse it,</p><p class='sl'><span class='br'></span>Because he burned the bones of the king of E′dom for lime.</p></div><div id='p18' class='par'><p class='sl'> <span id='dcv_2_2' class='dv dp'><a>2 </a></span>So I will send a fire into Mo′ab, and it will consume the fortified towers of Ke′ri·oth;<a class='mr'></a></p><p class='sz'><span class='br'></span>Mo′ab will die amid an uproar,</p><p class='sz'><span class='br'></span>With a war cry, with the sound of a horn.<a class='mr'></a></p></div><div id='p19' class='par'><p class='sl'> <span id='dcv_2_3' class='dv dp'><a>3 </a></span>I will remove the ruler<a class='fn'></a> from her midst</p><p class='sz'><span class='br'></span>And kill all her princes along with him,”<a class='mr'></a> says Jehovah.’</p></div><div id='p20' class='par'><p class='sl'> <span id='dcv_2_4' class='dv dx dp'><a>4 </a></span>This is what Jehovah says,</p><p class='sz'><span class='br'></span>‘For three revolts of Judah,<a class='mr'></a> and for four, I will not reverse it,</p><p class='sz'><span class='br'></span>Because they rejected the law<a class='fn'></a> of Jehovah,</p><p class='sz'><span class='br'></span>And because they did not keep his regulations;<a class='mr'></a></p><p class='sz'><span class='br'></span>But the same lies their forefathers followed have led them astray.<a class='mr'></a></p></div><div id='p21' class='par'><p class='sl'> <span id='dcv_2_5' class='dv dx dp'><a>5 </a></span>So I will send a fire into Judah,</p><p class='sz'><span class='br'></span>And it will consume the fortified towers of Jerusalem.’<a class='mr'></a></p></div><div id='p22' class='par'><p class='sl'> <span id='dcv_2_6' class='dv dx dp'><a>6 </a></span>This is what Jehovah says,</p><p class='sz'><span class='br'></span>‘For three revolts of Israel,<a class='mr'></a> and for four, I will not reverse it,</p><p class='sz'><span class='br'></span>Because they sell the righteous for silver,</p><p class='sz'><span class='br'></span>And the poor for a pair of sandals.<a class='mr'></a></p></div><div id='p23' class='par'><p class='sl'> <span id='dcv_2_7' class='dv dx dp'><a>7 </a></span>They trample the heads of the lowly into the dust of the earth,<a class='mr'></a></p><p class='sz'><span class='br'></span>And they block the path of the meek.<a class='mr'></a></p></div><div id='p24' class='par'><p class='sz'>A man and his father have relations with the same girl,</p><p class='sz'><span class='br'></span>Profaning my holy name.</p></div><div id='p25' class='par'><p class='sl'> <span id='dcv_2_8' class='dv dx dp'><a>8 </a></span>They stretch out next to every altar<a class='mr'></a> on garments they seized as security for a loan;<a class='fn'></a><a class='mr'></a></p><p class='sz'><span class='br'></span>And the wine they drink at the house<a class='fn'></a> of their gods was obtained from those they fined.’</p></div><div id='p26' class='par'><p class='sl'> <span id='dcv_2_9' class='dv dx dp'><a>9 </a></span>‘But it was I who annihilated the Am′or·ite before them,<a class='mr'></a></p><p class='sz'><span class='br'></span>Who was as tall as the cedars and as strong as the oaks;</p><p class='sz'><span class='br'></span>I destroyed his fruit above and his roots below.<a class='mr'></a></p></div><div id='p27' class='par'><p class='sl'><span id='dcv_2_10' class='dv dp'><a>10 </a></span>I brought you up out of the land of Egypt,<a class='mr'></a></p><p class='sz'><span class='br'></span>And I made you walk through the wilderness 40 years,<a class='mr'></a></p><p class='sz'><span class='br'></span>To take possession of the land of the Am′or·ite.</p></div><div id='p28' class='par'><p class='sl'><span id='dcv_2_11' class='dv dp'><a>11 </a></span>I raised up some of your sons as prophets<a class='mr'></a></p><p class='sz'><span class='br'></span>And some of your young men as Naz′i·rites.<a class='mr'></a></p></div><div id='p29' class='par'><p class='sz'>Is this not so, O people of Israel?’ declares Jehovah.</p></div><div id='p30' class='par'><p class='sl'><span id='dcv_2_12' class='dv dx dp'><a>12 </a></span>‘But you kept giving the Naz′i·rites wine to drink,<a class='mr'></a></p><p class='sz'><span class='br'></span>And you commanded the prophets: “You must not prophesy.”<a class='mr'></a></p></div><div id='p31' class='par'><p class='sl'><span id='dcv_2_13' class='dv dp'><a>13 </a></span>So I will crush you in your place,</p><p class='sz'><span class='br'></span>Just as a wagon loaded with cut grain crushes what is under it.</p></div><div id='p32' class='par'><p class='sl'><span id='dcv_2_14' class='dv dp'><a>14 </a></span>The swift one will have no place to flee,<a class='mr'></a></p><p class='sz'><span class='br'></span>The strong one will not retain his power,</p><p class='sz'><span class='br'></span>And no warrior will escape with his life.<a class='fn'></a></p></div><div id='p33' class='par'><p class='sl'><span id='dcv_2_15' class='dv dp'><a>15 </a></span>The bowman will not stand his ground,</p><p class='sz'><span class='br'></span>The swift of foot will not escape,</p><p class='sz'><span class='br'></span>And the horseman will not escape with his life.<a class='fn'></a></p></div><div id='p34' class='par'><p class='sl'><span id='dcv_2_16' class='dv dp'><a>16 </a></span>Even the most courageous<a class='fn'></a> among the warriors</p><p class='sz'><span class='br'></span>Will flee naked in that day,’<a class='mr'></a> declares Jehovah.”</p></div></div></text>
<text chap="3"><div class='document bible' dir='ltr'><div id='p35' class='par'><p class='sl'><span id='dcv_3_1' class='dc dp'><a>3 </a></span>“Hear this word that Jehovah has spoken concerning you, O people of Israel, concerning the whole family that I brought up out of the land of Egypt:</p></div><div id='p36' class='par'><p class='sl'> <span id='dcv_3_2' class='dv dx dp'><a>2 </a></span>‘You alone I have known out of all the families of the earth.<a class='mr'></a></p></div><div id='p37' class='par'><p class='sz'>That is why I will call you to account for all your errors.<a class='mr'></a></p></div><div id='p38' class='par'><p class='sl'> <span id='dcv_3_3' class='dv dx dp'><a>3 </a></span>Will two walk together unless they have agreed to meet?<a class='fn'></a></p></div><div id='p39' class='par'><p class='sl'> <span id='dcv_3_4' class='dv dx dp'><a>4 </a></span>Will a lion roar in the forest when it has no prey?</p></div><div id='p40' class='par'><p class='sz'>Will a young lion<a class='fn'></a> growl from its lair when it has caught nothing?</p></div><div id='p41' class='par'><p class='sl'> <span id='dcv_3_5' class='dv dp'><a>5 </a></span>Will a bird fall into a trap on the ground when there is no snare for it?<a class='fn'></a></p></div><div id='p42' class='par'><p class='sz'>Does a trap spring up from the ground when it has caught nothing?</p></div><div id='p43' class='par'><p class='sl'> <span id='dcv_3_6' class='dv dp'><a>6 </a></span>If a horn is blown in a city, do the people not tremble?</p></div><div id='p44' class='par'><p class='sz'>If a calamity occurs in the city, is it not Jehovah who has acted?</p></div><div id='p45' class='par'><p class='sl'> <span id='dcv_3_7' class='dv dx dp'><a>7 </a></span>For the Sovereign Lord Jehovah will not do a thing</p><p class='sz'><span class='br'></span>Unless he has revealed his confidential matter<a class='fn'></a> to his servants the prophets.<a class='mr'></a></p></div><div id='p46' class='par'><p class='sl'> <span id='dcv_3_8' class='dv dx dp'><a>8 </a></span>The lion has roared!<a class='mr'></a> Who will not be afraid?</p></div><div id='p47' class='par'><p class='sz'>The Sovereign Lord Jehovah has spoken! Who will not prophesy?’<a class='mr'></a></p></div><div id='p48' class='par'><p class='sl'> <span id='dcv_3_9' class='dv dp'><a>9 </a></span>‘Proclaim it on the fortified towers of Ash′dod</p><p class='sz'><span class='br'></span>And on the fortified towers in the land of Egypt.</p></div><div id='p49' class='par'><p class='sz'>Say: “Gather together against the mountains of Sa·mar′i·a;<a class='mr'></a></p><p class='sz'><span class='br'></span>See the turmoil in her midst</p><p class='sz'><span class='br'></span>And the defrauding within her.<a class='mr'></a></p></div><div id='p50' class='par'><p class='sl'><span id='dcv_3_10' class='dv dp'><a>10 </a></span>For they do not know how to do what is right,” declares Jehovah,</p><p class='sz'><span class='br'></span>“Those who are storing up violence and destruction in their fortified towers.”’</p></div><div id='p51' class='par'><p class='sl'><span id='dcv_3_11' class='dv dp'><a>11 </a></span>Therefore this is what the Sovereign Lord Jehovah says,</p><p class='sz'><span class='br'></span>‘An adversary will surround the land,<a class='mr'></a></p><p class='sz'><span class='br'></span>He will strip you of your strength,</p><p class='sz'><span class='br'></span>And your fortified towers will be plundered.’<a class='mr'></a></p></div><div id='p52' class='par'><p class='sl'><span id='dcv_3_12' class='dv dx dp'><a>12 </a></span>This is what Jehovah says,</p><p class='sz'><span class='br'></span>‘Just as the shepherd snatches away two legs or a piece of an ear from the mouth of the lion,</p><p class='sz'><span class='br'></span>That is how the people of Israel will be snatched away,</p><p class='sz'><span class='br'></span>Those now sitting in Sa·mar′i·a on splendid beds and on fine couches.’<a class='fn'></a><a class='mr'></a></p></div><div id='p53' class='par'><p class='sl'><span id='dcv_3_13' class='dv dp'><a>13 </a></span>‘Hear and warn<a class='fn'></a> the house of Jacob,’ declares the Sovereign Lord Jehovah, the God of armies.</p></div><div id='p54' class='par'><p class='sl'><span id='dcv_3_14' class='dv dx dp'><a>14 </a></span>‘For in the day I call Israel to account for all his revolts,<a class='fn'></a><a class='mr'></a></p><p class='sz'><span class='br'></span>I will also call for an accounting against the altars of Beth′el;<a class='mr'></a></p><p class='sz'><span class='br'></span>The horns of the altar will be cut off and fall to the earth.<a class='mr'></a></p></div><div id='p55' class='par'><p class='sl'><span id='dcv_3_15' class='dv dx dp'><a>15 </a></span>I will strike down the winter house along with the summer house.’</p></div><div id='p56' class='par'><p class='sz'>‘The houses of ivory will perish,<a class='mr'></a></p><p class='sz'><span class='br'></span>And the great<a class='fn'></a> houses will come to their end,’<a class='mr'></a> declares Jehovah.”</p></div></div></text>
<text chap="4"><div class='document bible' dir='ltr'><div id='p57' class='par'><p class='sl'><span id='dcv_4_1' class='dc dx dp'><a>4 </a></span>“Hear this word, you cows of Ba′shan,</p><p class='sz'><span class='br'></span>Who are on the mountain of Sa·mar′i·a,<a class='mr'></a></p><p class='sz'><span class='br'></span>You women who are defrauding the lowly<a class='mr'></a> and crushing the poor,</p><p class='sz'><span class='br'></span>Who say to their husbands,<a class='fn'></a> ‘Bring us something to drink!’</p></div><div id='p58' class='par'><p class='sl'> <span id='dcv_4_2' class='dv dx dp'><a>2 </a></span>The Sovereign Lord Jehovah has sworn by his holiness,</p><p class='sz'><span class='br'></span>‘“Look! The days are coming upon you when he will lift you up with butcher hooks</p><p class='sz'><span class='br'></span>And the rest of you with fishhooks.</p></div><div id='p59' class='par'><p class='sl'> <span id='dcv_4_3' class='dv dx dp'><a>3 </a></span>You will go out through the breaches in the wall, each one straight ahead;</p><p class='sz'><span class='br'></span>And you will be cast out to Har′mon,” declares Jehovah.’</p></div><div id='p60' class='par'><p class='sl'> <span id='dcv_4_4' class='dv dx dp'><a>4 </a></span>‘Come to Beth′el and commit transgression,<a class='fn'></a><a class='mr'></a></p><p class='sz'><span class='br'></span>To Gil′gal and transgress even more!<a class='mr'></a></p></div><div id='p61' class='par'><p class='sz'>Bring your sacrifices<a class='mr'></a> in the morning,</p><p class='sz'><span class='br'></span>And your tithes<a class='fn'></a><a class='mr'></a> on the third day.</p></div><div id='p62' class='par'><p class='sl'> <span id='dcv_4_5' class='dv dx dp'><a>5 </a></span>Burn a thanksgiving sacrifice of leavened bread;<a class='mr'></a></p><p class='sz'><span class='br'></span>Loudly proclaim your voluntary offerings!</p></div><div id='p63' class='par'><p class='sz'>For that is what you love to do, O people of Israel,’ declares the Sovereign Lord Jehovah.</p></div><div id='p64' class='par'><p class='sl'> <span id='dcv_4_6' class='dv dx dp'><a>6 </a></span>‘And for my part, I made your teeth clean of food<a class='fn'></a> in all your cities</p><p class='sz'><span class='br'></span>And caused a lack of bread in all your houses;<a class='mr'></a></p><p class='sz'><span class='br'></span>But you did not come back to me,’<a class='mr'></a> declares Jehovah.</p></div><div id='p65' class='par'><p class='sl'> <span id='dcv_4_7' class='dv dp'><a>7 </a></span>‘I also withheld rain from you three months before the harvest;<a class='mr'></a></p><p class='sz'><span class='br'></span>I made it rain on one city but not on another city.</p></div><div id='p66' class='par'><p class='sz'>One plot of land would have rain,</p><p class='sz'><span class='br'></span>But another plot of land where there was no rain would dry up.</p></div><div id='p67' class='par'><p class='sl'> <span id='dcv_4_8' class='dv dp'><a>8 </a></span>People of two or three cities staggered to one city to drink water,<a class='mr'></a></p><p class='sz'><span class='br'></span>And they would not get satisfied;</p><p class='sz'><span class='br'></span>But you did not come back to me,’<a class='mr'></a> declares Jehovah.</p></div><div id='p68' class='par'><p class='sl'> <span id='dcv_4_9' class='dv dx dp'><a>9 </a></span>‘I struck you with scorching heat and mildew.<a class='mr'></a></p></div><div id='p69' class='par'><p class='sz'>You multiplied your gardens and vineyards,</p><p class='sz'><span class='br'></span>But the locust would devour your fig trees and olive trees;<a class='mr'></a></p><p class='sz'><span class='br'></span>And you still did not come back to me,’<a class='mr'></a> declares Jehovah.</p></div><div id='p70' class='par'><p class='sl'><span id='dcv_4_10' class='dv dp'><a>10 </a></span>‘I sent among you a pestilence like that of Egypt.<a class='mr'></a></p></div><div id='p71' class='par'><p class='sz'>With the sword I killed your young men<a class='mr'></a> and captured your horses.<a class='mr'></a></p></div><div id='p72' class='par'><p class='sz'>I made the stench of your camps rise up into your nostrils;<a class='mr'></a></p><p class='sz'><span class='br'></span>But you did not come back to me,’ declares Jehovah.</p></div><div id='p73' class='par'><p class='sl'><span id='dcv_4_11' class='dv dp'><a>11 </a></span>‘I caused an overthrow among you</p><p class='sz'><span class='br'></span>Like God’s overthrow of Sod′om and Go·mor′rah.<a class='mr'></a></p></div><div id='p74' class='par'><p class='sz'>And you were like a log snatched out of the fire;</p><p class='sz'><span class='br'></span>But you did not come back to me,’<a class='mr'></a> declares Jehovah.</p></div><div id='p75' class='par'><p class='sl'><span id='dcv_4_12' class='dv dx dp'><a>12 </a></span>So that is what I will do to you, O Israel.</p></div><div id='p76' class='par'><p class='sz'>Because this is what I will do to you,</p><p class='sz'><span class='br'></span>Get ready to meet your God, O Israel.</p></div><div id='p77' class='par'><p class='sl'><span id='dcv_4_13' class='dv dp'><a>13 </a></span>For look! he is the One who formed the mountains<a class='mr'></a> and created the wind;<a class='mr'></a></p><p class='sz'><span class='br'></span>He tells man what His thoughts are,</p><p class='sz'><span class='br'></span>He turns the dawn into darkness,<a class='mr'></a></p><p class='sz'><span class='br'></span>And he treads on earth’s high places;<a class='mr'></a></p><p class='sz'><span class='br'></span>Jehovah the God of armies is his name.”</p></div></div></text>
<text chap="5"><div class='document bible' dir='ltr'><div id='p78' class='par'><p class='sl'><span id='dcv_5_1' class='dc dp'><a>5 </a></span>“Hear this word that I am taking up against you as a dirge,<a class='fn'></a> O house of Israel:</p></div><div id='p79' class='par'><p class='sl'> <span id='dcv_5_2' class='dv dx dp'><a>2 </a></span>‘The virgin, Israel, has fallen;</p><p class='sz'><span class='br'></span>She cannot get up again.</p></div><div id='p80' class='par'><p class='sz'>She has been abandoned on her own ground;</p><p class='sz'><span class='br'></span>There is no one to raise her up.’</p></div><div id='p81' class='par'><p class='sb'><span id='dcv_5_3' class='dv dp'><a>3 </a></span>“For this is what the Sovereign Lord Jehovah says:</p></div><div id='p82' class='par'><p class='sz'>‘The city that marches out with a thousand will have a hundred left;</p><p class='sz'><span class='br'></span>And the one that goes out with a hundred will have ten left, for the house of Israel.’<a class='mr'></a></p></div><div id='p83' class='par'><p class='sb'><span id='dcv_5_4' class='dv dp'><a>4 </a></span>“For this is what Jehovah says to the house of Israel:</p></div><div id='p84' class='par'><p class='sz'>‘Search for me and keep living.<a class='mr'></a></p></div><div id='p85' class='par'><p class='sl'> <span id='dcv_5_5' class='dv dx dp'><a>5 </a></span>Do not search for Beth′el,<a class='mr'></a></p><p class='sz'><span class='br'></span>Do not go to Gil′gal<a class='mr'></a> or pass over to Be′er-she′ba<span class='alt'>,</span><a class='mr'></a></p><p class='sz'><span class='br'></span>For Gil′gal will certainly go into exile,<a class='mr'></a></p><p class='sz'><span class='br'></span>And Beth′el will come to nothing.<a class='fn'></a></p></div><div id='p86' class='par'><p class='sl'> <span id='dcv_5_6' class='dv dp'><a>6 </a></span>Search for Jehovah, and keep living,<a class='mr'></a></p><p class='sz'><span class='br'></span>So that he does not burst out like a fire on the house of Joseph,</p><p class='sz'><span class='br'></span>Consuming Beth′el, with no one to extinguish it.</p></div><div id='p87' class='par'><p class='sl'> <span id='dcv_5_7' class='dv dp'><a>7 </a></span>You turn justice into wormwood,<a class='fn'></a></p><p class='sz'><span class='br'></span>And you cast righteousness to the earth.<a class='mr'></a></p></div><div id='p88' class='par'><p class='sl'> <span id='dcv_5_8' class='dv dx dp'><a>8 </a></span>The One who made the Ki′mah constellation<a class='fn'></a> and the Ke′sil constellation,<a class='fn'></a><a class='mr'></a></p><p class='sz'><span class='br'></span>The One who turns deep shadow into morning,</p><p class='sz'><span class='br'></span>The One who makes day as dark as night,<a class='mr'></a></p><p class='sz'><span class='br'></span>The One who summons the waters of the sea</p><p class='sz'><span class='br'></span>To pour them out on the surface of the earth<a class='mr'></a></p><p class='sz'><span class='br'></span>—Jehovah is his name.</p></div><div id='p89' class='par'><p class='sl'> <span id='dcv_5_9' class='dv dp'><a>9 </a></span>He will cause destruction to burst out against the strong,</p><p class='sz'><span class='br'></span>Bringing destruction on fortified places.</p></div><div id='p90' class='par'><p class='sl'><span id='dcv_5_10' class='dv dx dp'><a>10 </a></span>They hate those who give reproof in the city gate,</p><p class='sz'><span class='br'></span>And they detest those who speak truthfully.<a class='mr'></a></p></div><div id='p91' class='par'><p class='sl'><span id='dcv_5_11' class='dv dx dp'><a>11 </a></span>Because you demand farm rent<a class='fn'></a> from the poor</p><p class='sz'><span class='br'></span>And you take his grain as tribute,<a class='mr'></a></p><p class='sz'><span class='br'></span>You will not keep dwelling in the houses of hewn stone that you have built<a class='mr'></a></p><p class='sz'><span class='br'></span>Nor drink the wine from the choice vineyards that you have planted.<a class='mr'></a></p></div><div id='p92' class='par'><p class='sl'><span id='dcv_5_12' class='dv dx dp'><a>12 </a></span>For I know how many your revolts<a class='fn'></a> are</p><p class='sz'><span class='br'></span>And how great your sins are</p><p class='sz'><span class='br'></span>—You harass the righteous,</p><p class='sz'><span class='br'></span>You take bribes,<a class='fn'></a></p><p class='sz'><span class='br'></span>And you deny the rights of the poor in the city gate.<a class='mr'></a></p></div><div id='p93' class='par'><p class='sl'><span id='dcv_5_13' class='dv dp'><a>13 </a></span>Therefore, those with insight will keep silent at that time,</p><p class='sz'><span class='br'></span>For it will be a time of calamity.<a class='mr'></a></p></div><div id='p94' class='par'><p class='sl'><span id='dcv_5_14' class='dv dp'><a>14 </a></span>Search for what is good, and not what is bad,<a class='mr'></a></p><p class='sz'><span class='br'></span>So that you may keep living.<a class='mr'></a></p></div><div id='p95' class='par'><p class='sz'>Then Jehovah the God of armies may be with you,</p><p class='sz'><span class='br'></span>Just as you say he is.<a class='mr'></a></p></div><div id='p96' class='par'><p class='sl'><span id='dcv_5_15' class='dv dx dp'><a>15 </a></span>Hate what is bad, and love what is good,<a class='mr'></a></p><p class='sz'><span class='br'></span>Let justice prevail in the city gate.<a class='mr'></a></p></div><div id='p97' class='par'><p class='sz'>It may be that Jehovah the God of armies</p><p class='sz'><span class='br'></span>Will show favor to the remaining ones of Joseph.’<a class='mr'></a></p></div><div id='p98' class='par'><p class='sb'><span id='dcv_5_16' class='dv dp'><a>16 </a></span>“Therefore this is what Jehovah the God of armies, Jehovah, says:</p></div><div id='p99' class='par'><p class='sz'>‘In all the public squares there will be wailing,</p><p class='sz'><span class='br'></span>And in all the streets they will say, “Alas, alas!”</p></div><div id='p100' class='par'><p class='sz'>They will call on the farmers to mourn</p><p class='sz'><span class='br'></span>And the professional mourners to wail.’</p></div><div id='p101' class='par'><p class='sl'><span id='dcv_5_17' class='dv dp'><a>17 </a></span>‘In every vineyard there will be wailing;<a class='mr'></a></p><p class='sz'><span class='br'></span>For I will pass through your midst,’ says Jehovah.</p></div><div id='p102' class='par'><p class='sl'><span id='dcv_5_18' class='dv dx dp'><a>18 </a></span>‘Woe to those who yearn for the day of Jehovah!<a class='mr'></a></p></div><div id='p103' class='par'><p class='sz'>What, then, will the day of Jehovah mean for you?<a class='mr'></a></p></div><div id='p104' class='par'><p class='sz'>It will be darkness, and not light.<a class='mr'></a></p></div><div id='p105' class='par'><p class='sl'><span id='dcv_5_19' class='dv dx dp'><a>19 </a></span>It will be like a man who flees from a lion and is confronted by a bear,</p><p class='sz'><span class='br'></span>And when he enters his house and leans his hand against the wall, a snake bites him.</p></div><div id='p106' class='par'><p class='sl'><span id='dcv_5_20' class='dv dp'><a>20 </a></span>Will not the day of Jehovah be darkness, and not light;</p><p class='sz'><span class='br'></span>Will it not have gloom, and not brightness?</p></div><div id='p107' class='par'><p class='sl'><span id='dcv_5_21' class='dv dx dp'><a>21 </a></span>I hate, I despise your festivals,<a class='mr'></a></p><p class='sz'><span class='br'></span>And I take no pleasure in the aroma of your solemn assemblies.</p></div><div id='p108' class='par'><p class='sl'><span id='dcv_5_22' class='dv dp'><a>22 </a></span>Even if you offer me whole burnt offerings and gift offerings,</p><p class='sz'><span class='br'></span>I will find no pleasure in them;<a class='mr'></a></p><p class='sz'><span class='br'></span>And I will not look with favor on your communion sacrifices of fattened animals.<a class='mr'></a></p></div><div id='p109' class='par'><p class='sl'><span id='dcv_5_23' class='dv dp'><a>23 </a></span>Spare me the din of your songs;</p><p class='sz'><span class='br'></span>And let me not hear the melodies of your stringed instruments.<a class='mr'></a></p></div><div id='p110' class='par'><p class='sl'><span id='dcv_5_24' class='dv dp'><a>24 </a></span>Let justice flow down like waters,<a class='mr'></a></p><p class='sz'><span class='br'></span>And righteousness like an ever-flowing stream.</p></div><div id='p111' class='par'><p class='sl'><span id='dcv_5_25' class='dv dp'><a>25 </a></span>Did you bring me sacrifices and gift offerings</p><p class='sz'><span class='br'></span>For those 40 years in the wilderness, O house of Israel?<a class='mr'></a></p></div><div id='p112' class='par'><p class='sl'><span id='dcv_5_26' class='dv dx dp'><a>26 </a></span>Now you will have to carry away Sak′kuth your king and Kai′wan,<a class='fn'></a></p><p class='sz'><span class='br'></span>Your images, the star of your god, whom you made for yourselves,</p><p class='sl'><span class='br'></span><span id='dcv_5_27' class='dv dx dp'><a>27 </a></span>And I will send you into exile beyond Damascus,’<a class='mr'></a> says he whose name is Jehovah the God of armies.”<a class='mr'></a></p></div></div></text>
<text chap="6"><div class='document bible' dir='ltr'><div id='p113' class='par'><p class='sl'><span id='dcv_6_1' class='dc dp'><a>6 </a></span>“Woe to the self-assured<a class='fn'></a> ones in Zion,</p><p class='sz'><span class='br'></span>To those feeling secure in the mountain of Sa·mar′i·a,<a class='mr'></a></p><p class='sz'><span class='br'></span>The prominent men of the foremost of nations,</p><p class='sz'><span class='br'></span>Those to whom the house of Israel comes!</p></div><div id='p114' class='par'><p class='sl'> <span id='dcv_6_2' class='dv dx dp'><a>2 </a></span>Cross over to Cal′neh and see.</p></div><div id='p115' class='par'><p class='sz'>Go from there to Great Ha′math,<a class='mr'></a></p><p class='sz'><span class='br'></span>And go down to Gath of the Phi·lis′tines.</p></div><div id='p116' class='par'><p class='sz'>Are they better than these kingdoms,<a class='fn'></a></p><p class='sz'><span class='br'></span>Or is their territory larger than yours?</p></div><div id='p117' class='par'><p class='sl'> <span id='dcv_6_3' class='dv dx dp'><a>3 </a></span>Are you putting out of your mind the day of calamity<a class='mr'></a></p><p class='sz'><span class='br'></span>And bringing in a reign<a class='fn'></a> of violence?<a class='mr'></a></p></div><div id='p118' class='par'><p class='sl'> <span id='dcv_6_4' class='dv dx dp'><a>4 </a></span>They lie on beds of ivory<a class='mr'></a> and sprawl out on couches,<a class='mr'></a></p><p class='sz'><span class='br'></span>Eating the rams of the flock and the fattened calves;<a class='fn'></a><a class='mr'></a></p><p class='sl'><span class='br'></span> <span id='dcv_6_5' class='dv dx dp'><a>5 </a></span>They improvise songs to the sound of the harp,<a class='fn'></a><a class='mr'></a></p><p class='sz'><span class='br'></span>And like David, they invent musical instruments;<a class='mr'></a></p><p class='sl'><span class='br'></span> <span id='dcv_6_6' class='dv dx dp'><a>6 </a></span>They drink wine by the bowlful<a class='mr'></a></p><p class='sz'><span class='br'></span>And anoint themselves with the choicest oils.</p></div><div id='p119' class='par'><p class='sz'>But they are unconcerned about<a class='fn'></a> the catastrophe of Joseph.<a class='mr'></a></p></div><div id='p120' class='par'><p class='sl'> <span id='dcv_6_7' class='dv dp'><a>7 </a></span>So they will go into exile at the head of the exiles,<a class='mr'></a></p><p class='sz'><span class='br'></span>And the revelry of those sprawled out will come to an end.</p></div><div id='p121' class='par'><p class='sl'> <span id='dcv_6_8' class='dv dp'><a>8 </a></span>‘The Sovereign Lord Jehovah has sworn by himself,’<a class='fn'></a><a class='mr'></a> declares Jehovah the God of armies,</p><p class='sz'><span class='br'></span>‘“I detest the pride of Jacob,<a class='mr'></a></p><p class='sz'><span class='br'></span>I hate his fortified towers,<a class='mr'></a></p><p class='sz'><span class='br'></span>And I will hand over the city and what fills it.<a class='mr'></a></p></div><div id='p122' class='par'><p class='sb'><span id='dcv_6_9' class='dv dp'><a>9 </a></span>“‘“And if ten men are left in one house, they will also die. <span id='dcv_6_10' class='dv dp'><a>10 </a></span>A relative<a class='fn'></a> will come to carry them out and burn them one by one. He will bring their bones out from the house; then he will say to whoever is in the inner rooms of the house, ‘Are there any more with you?’ And he will say, ‘Nobody!’ Then he will say, ‘Keep silent! For it is not the time to make any mention of the name of Jehovah.’”</p></div><div id='p123' class='par'><p class='sl'><span id='dcv_6_11' class='dv dp'><a>11 </a></span>For it is Jehovah giving the command,<a class='mr'></a></p><p class='sz'><span class='br'></span>And he will strike down the great house into rubble,</p><p class='sz'><span class='br'></span>And the small house into debris.<a class='mr'></a></p></div><div id='p124' class='par'><p class='sl'><span id='dcv_6_12' class='dv dx dp'><a>12 </a></span>Do horses run on a crag,</p><p class='sz'><span class='br'></span>Or will one plow there with cattle?</p></div><div id='p125' class='par'><p class='sz'>For you have turned justice into a poisonous plant,</p><p class='sz'><span class='br'></span>And the fruit of righteousness into wormwood.<a class='fn'></a><a class='mr'></a></p></div><div id='p126' class='par'><p class='sl'><span id='dcv_6_13' class='dv dx dp'><a>13 </a></span>You rejoice over what is worthless,</p><p class='sz'><span class='br'></span>And you say, “Have we not become powerful<a class='fn'></a> in our own strength?”<a class='mr'></a></p></div><div id='p127' class='par'><p class='sl'><span id='dcv_6_14' class='dv dx dp'><a>14 </a></span>Therefore, O house of Israel, I will bring against you a nation,’<a class='mr'></a> declares Jehovah the God of armies,</p><p class='sz'><span class='br'></span>‘And they will oppress you from Le′bo-ha′math<a class='fn'></a><a class='mr'></a> down to the Wadi<a class='fn'></a> of the Ar′a·bah.’”</p></div></div></text>
<text chap="7"><div class='document bible' dir='ltr'><div id='p128' class='par'><p class='sb'><span id='dcv_7_1' class='dc dx dp'><a>7 </a></span>This is what the Sovereign Lord Jehovah showed me: Look! He formed a locust swarm when the late crop<a class='fn'></a> was beginning to come up. This was the later crop after the king’s hay had been cut. <span id='dcv_7_2' class='dv dp'><a>2 </a></span>When the swarm finished eating up the vegetation of the land, I said: “O Sovereign Lord Jehovah, please forgive!<a class='mr'></a> How can Jacob survive?<a class='fn'></a> For he is weak!”<a class='mr'></a></p></div><div id='p129' class='par'><p class='sb'><span id='dcv_7_3' class='dv dx dp'><a>3 </a></span>So Jehovah reconsidered<a class='fn'></a> this.<a class='mr'></a> “It will not happen,” Jehovah said.</p></div><div id='p130' class='par'><p class='sb'><span id='dcv_7_4' class='dv dx dp'><a>4 </a></span>This is what the Sovereign Lord Jehovah showed me: Look! The Sovereign Lord Jehovah called for a punishment by fire. It consumed the vast deep waters, and it consumed a portion of the land. <span id='dcv_7_5' class='dv dp'><a>5 </a></span>Then I said: “O Sovereign Lord Jehovah, please hold this back.<a class='mr'></a> How can Jacob survive?<a class='fn'></a> For he is weak!”<a class='mr'></a></p></div><div id='p131' class='par'><p class='sb'><span id='dcv_7_6' class='dv dx dp'><a>6 </a></span>So Jehovah reconsidered<a class='fn'></a> this.<a class='mr'></a> “That too will not happen,” the Sovereign Lord Jehovah said.</p></div><div id='p132' class='par'><p class='sb'><span id='dcv_7_7' class='dv dx dp'><a>7 </a></span>This is what he showed me: Look! Jehovah was standing on a wall made with a plumb line,<a class='fn'></a> and there was a plumb line in his hand. <span id='dcv_7_8' class='dv dx dp'><a>8 </a></span>Then Jehovah said to me: “What do you see, A′mos?” So I said: “A plumb line.” Jehovah then said: “Here I am putting a plumb line among my people Israel. I will no longer pardon them.<a class='mr'></a> <span id='dcv_7_9' class='dv dx dp'><a>9 </a></span>The high places of Isaac<a class='mr'></a> will be desolated, and the sanctuaries of Israel will be devastated;<a class='mr'></a> and I will come against the house of Jer·o·bo′am with a sword.”<a class='mr'></a></p></div><div id='p133' class='par'><p class='sb'><span id='dcv_7_10' class='dv dx dp'><a>10 </a></span>Am·a·zi′ah the priest of Beth′el<a class='mr'></a> sent this message to King Jer·o·bo′am<a class='mr'></a> of Israel: “A′mos is conspiring against you right in the midst of the house of Israel.<a class='mr'></a> The land cannot put up with all his words.<a class='mr'></a> <span id='dcv_7_11' class='dv dx dp'><a>11 </a></span>For this is what A′mos says, ‘Jer·o·bo′am will die by the sword, and Israel will surely go into exile from its land.’”<a class='mr'></a></p></div><div id='p134' class='par'><p class='sb'><span id='dcv_7_12' class='dv dx dp'><a>12 </a></span>Am·a·zi′ah then said to A′mos: “O visionary, go, run away to the land of Judah, earn your bread<a class='fn'></a> there, and there you may prophesy.<a class='mr'></a> <span id='dcv_7_13' class='dv dx dp'><a>13 </a></span>But you must no longer prophesy at Beth′el,<a class='mr'></a> for it is the sanctuary of a king<a class='mr'></a> and the house of a kingdom.”</p></div><div id='p135' class='par'><p class='sb'><span id='dcv_7_14' class='dv dx dp'><a>14 </a></span>Then A′mos answered Am·a·zi′ah: “I was not a prophet nor the son of a prophet; but I was a herdsman,<a class='mr'></a> and I took care of sycamore fig trees.<a class='fn'></a> <span id='dcv_7_15' class='dv dx dp'><a>15 </a></span>But Jehovah took me away from following the flock, and Jehovah said to me, ‘Go, prophesy to my people Israel.’<a class='mr'></a> <span id='dcv_7_16' class='dv dp'><a>16 </a></span>So now hear the word of Jehovah: ‘You are saying, “Do not prophesy against Israel,<a class='mr'></a> and do not preach<a class='mr'></a> against the house of Isaac.” <span id='dcv_7_17' class='dv dp'><a>17 </a></span>Therefore this is what Jehovah says: “Your wife will become a prostitute in the city, and your sons and your daughters will fall by the sword. Your land will be apportioned out with a measuring line, and you yourself will die in an unclean land; and Israel will surely go into exile from its land.”’”<a class='mr'></a></p></div></div></text>
<text chap="8"><div class='document bible' dir='ltr'><div id='p136' class='par'><p class='sb'><span id='dcv_8_1' class='dc dp'><a>8 </a></span>This is what the Sovereign Lord Jehovah showed me: Look! There was a basket of summer fruit. <span id='dcv_8_2' class='dv dx dp'><a>2 </a></span>Then he said, “What do you see, A′mos?” I replied, “A basket of summer fruit.” Then Jehovah said to me: “The end has come for my people Israel. I will no longer pardon them.<a class='mr'></a> <span id='dcv_8_3' class='dv dp'><a>3 </a></span>‘The songs of the temple will turn into wailing in that day,’<a class='mr'></a> declares the Sovereign Lord Jehovah. ‘There will be many carcasses thrown everywhere<a class='mr'></a>—hush!’</p></div><div id='p137' class='par'><p class='sl'> <span id='dcv_8_4' class='dv dp'><a>4 </a></span>Hear this, you who trample on the poor</p><p class='sz'><span class='br'></span>And who bring the meek of the land to an end,<a class='mr'></a></p><p class='sl'><span class='br'></span> <span id='dcv_8_5' class='dv dx dp'><a>5 </a></span>Who say, ‘When will the new moon festival be over,<a class='mr'></a> that we may sell our grain,</p><p class='sz'><span class='br'></span>And the Sabbath,<a class='mr'></a> that we may offer grain for sale?</p></div><div id='p138' class='par'><p class='sz'>So that we may make the e′phah<a class='fn'></a> measure smaller</p><p class='sz'><span class='br'></span>And the shekel<a class='fn'></a> weight greater,</p><p class='sz'><span class='br'></span>To falsify our scales of deception;<a class='mr'></a></p><p class='sl'><span class='br'></span> <span id='dcv_8_6' class='dv dx dp'><a>6 </a></span>So that we may buy the needy for silver</p><p class='sz'><span class='br'></span>And the poor for a pair of sandals,<a class='mr'></a></p><p class='sz'><span class='br'></span>And sell the worthless part of the grain.’</p></div><div id='p139' class='par'><p class='sl'> <span id='dcv_8_7' class='dv dp'><a>7 </a></span>Jehovah has sworn by the Pride of Jacob,<a class='mr'></a></p><p class='sz'><span class='br'></span>‘Never will I forget all their deeds.<a class='mr'></a></p></div><div id='p140' class='par'><p class='sl'> <span id='dcv_8_8' class='dv dp'><a>8 </a></span>On this account the land<a class='fn'></a> will tremble,</p><p class='sz'><span class='br'></span>And every inhabitant in it will mourn.<a class='mr'></a></p></div><div id='p141' class='par'><p class='sz'>Will it not all rise like the Nile,</p><p class='sz'><span class='br'></span>And surge and sink down like the Nile of Egypt?’<a class='mr'></a></p></div><div id='p142' class='par'><p class='sl'> <span id='dcv_8_9' class='dv dp'><a>9 </a></span>‘In that day,’ declares the Sovereign Lord Jehovah,</p><p class='sz'><span class='br'></span>‘I will make the sun go down at high noon,</p><p class='sz'><span class='br'></span>And I will darken the land on a bright day.<a class='mr'></a></p></div><div id='p143' class='par'><p class='sl'><span id='dcv_8_10' class='dv dp'><a>10 </a></span>I will turn your festivals into mourning<a class='mr'></a></p><p class='sz'><span class='br'></span>And all your songs into dirges.<a class='fn'></a></p></div><div id='p144' class='par'><p class='sz'>I will put sackcloth on all hips and make every head bald;</p><p class='sz'><span class='br'></span>I will make it like the mourning for an only son,</p><p class='sz'><span class='br'></span>And the end of it like a bitter day.’</p></div><div id='p145' class='par'><p class='sl'><span id='dcv_8_11' class='dv dx dp'><a>11 </a></span>‘Look! The days are coming,’ declares the Sovereign Lord Jehovah,</p><p class='sz'><span class='br'></span>‘When I will send a famine into the land,</p><p class='sz'><span class='br'></span>Not a famine for bread or a thirst for water,</p><p class='sz'><span class='br'></span>But for hearing the words of Jehovah.<a class='mr'></a></p></div><div id='p146' class='par'><p class='sl'><span id='dcv_8_12' class='dv dp'><a>12 </a></span>They will stagger from sea to sea</p><p class='sz'><span class='br'></span>And from the north to the east.<a class='fn'></a></p></div><div id='p147' class='par'><p class='sz'>They will rove about searching for the word of Jehovah, but they will not find it.</p></div><div id='p148' class='par'><p class='sl'><span id='dcv_8_13' class='dv dp'><a>13 </a></span>In that day beautiful virgins will faint,</p><p class='sz'><span class='br'></span>Also young men, because of the thirst;</p><p class='sl'><span class='br'></span><span id='dcv_8_14' class='dv dx dp'><a>14 </a></span>Those who swear by the guilt of Sa·mar′i·a<a class='mr'></a> and who say,</p><p class='sz'><span class='br'></span>“As surely as your god lives, O Dan!”<a class='mr'></a></p></div><div id='p149' class='par'><p class='sz'>And, “As surely as the way of Be′er-she′ba<a class='mr'></a> lives!”</p></div><div id='p150' class='par'><p class='sz'>They will fall, and they will not rise up again.’”<a class='mr'></a></p></div></div></text>
<text chap="9"><div class='document bible' dir='ltr'><div id='p151' class='par'><p class='sb'><span id='dcv_9_1' class='dc dp'><a>9 </a></span>I saw Jehovah<a class='mr'></a> stationed above the altar, and he said: “Strike the head of the pillar, and the thresholds will shake. Cut them off at the head, and I will kill the last of them with the sword. No one who flees will get away, and no one trying to escape will succeed.<a class='mr'></a></p></div><div id='p152' class='par'><p class='sl'> <span id='dcv_9_2' class='dv dx dp'><a>2 </a></span>If they dig down into the Grave,<a class='fn'></a></p><p class='sz'><span class='br'></span>From there my hand will take them;</p><p class='sz'><span class='br'></span>And if they go up to the heavens,</p><p class='sz'><span class='br'></span>From there I will bring them down.</p></div><div id='p153' class='par'><p class='sl'> <span id='dcv_9_3' class='dv dx dp'><a>3 </a></span>And if they hide themselves on the top of Car′mel,</p><p class='sz'><span class='br'></span>From there I will search them out and take them.<a class='mr'></a></p></div><div id='p154' class='par'><p class='sz'>If they conceal themselves from my eyes on the bottom of the sea,</p><p class='sz'><span class='br'></span>There I will command the serpent to bite them.</p></div><div id='p155' class='par'><p class='sl'> <span id='dcv_9_4' class='dv dp'><a>4 </a></span>If they go into captivity before their enemies,</p><p class='sz'><span class='br'></span>From there I will command the sword, and it will kill them;<a class='mr'></a></p><p class='sz'><span class='br'></span>I will fix my eyes on them for bad, and not for good.<a class='mr'></a></p></div><div id='p156' class='par'><p class='sl'> <span id='dcv_9_5' class='dv dp'><a>5 </a></span>For the Sovereign Lord, Jehovah of the armies, is the One who touches the land,<a class='fn'></a></p><p class='sz'><span class='br'></span>So that it melts,<a class='mr'></a> and all its inhabitants will mourn;<a class='mr'></a></p><p class='sz'><span class='br'></span>And all of it will rise like the Nile,</p><p class='sz'><span class='br'></span>And sink down like the Nile of Egypt.<a class='mr'></a></p></div><div id='p157' class='par'><p class='sl'> <span id='dcv_9_6' class='dv dx dp'><a>6 </a></span>‘The one who builds his stairs in the heavens</p><p class='sz'><span class='br'></span>And establishes his structure<a class='fn'></a> over the earth;</p><p class='sz'><span class='br'></span>The one who summons the waters of the sea,</p><p class='sz'><span class='br'></span>To pour them out on the surface of the earth<a class='mr'></a></p><p class='sz'><span class='br'></span>—Jehovah is his name.’<a class='mr'></a></p></div><div id='p158' class='par'><p class='sl'> <span id='dcv_9_7' class='dv dx dp'><a>7 </a></span>‘Are you not like the sons of the Cush′ites to me, O people of Israel?’ declares Jehovah.</p></div><div id='p159' class='par'><p class='sz'>‘Did I not bring Israel up out of the land of Egypt,<a class='mr'></a></p><p class='sz'><span class='br'></span>The Phi·lis′tines out of Crete,<a class='mr'></a> and Syria out of Kir?’<a class='mr'></a></p></div><div id='p160' class='par'><p class='sl'> <span id='dcv_9_8' class='dv dx dp'><a>8 </a></span>‘Look! The eyes of the Sovereign Lord Jehovah are on the sinful kingdom,</p><p class='sz'><span class='br'></span>And he will annihilate it from the surface of the land.<a class='mr'></a></p></div><div id='p161' class='par'><p class='sz'>But I will not completely annihilate the house of Jacob,’<a class='mr'></a> declares Jehovah.</p></div><div id='p162' class='par'><p class='sl'> <span id='dcv_9_9' class='dv dp'><a>9 </a></span>‘For look! I am giving the command,</p><p class='sz'><span class='br'></span>And I will shake the house of Israel among all the nations,<a class='mr'></a></p><p class='sz'><span class='br'></span>Just as one shakes a sieve,</p><p class='sz'><span class='br'></span>And not a pebble falls to the ground.</p></div><div id='p163' class='par'><p class='sl'><span id='dcv_9_10' class='dv dx dp'><a>10 </a></span>They will die by the sword, all the sinners of my people,</p><p class='sz'><span class='br'></span>Those who are saying, “The calamity will not come near us or reach us.”’</p></div><div id='p164' class='par'><p class='sl'><span id='dcv_9_11' class='dv dx dp'><a>11 </a></span>‘In that day I will raise up the booth<a class='fn'></a> of David<a class='mr'></a> that is fallen,</p><p class='sz'><span class='br'></span>I will repair the<a class='fn'></a> breaches,</p><p class='sz'><span class='br'></span>And I will restore its ruins;</p><p class='sz'><span class='br'></span>I will rebuild it as in the days of long ago,<a class='mr'></a></p><p class='sl'><span class='br'></span><span id='dcv_9_12' class='dv dx dp'><a>12 </a></span>So that they may take possession of what is remaining of E′dom,<a class='mr'></a></p><p class='sz'><span class='br'></span>And all the nations on whom my name has been called,’ declares Jehovah, who is doing this.</p></div><div id='p165' class='par'><p class='sl'><span id='dcv_9_13' class='dv dx dp'><a>13 </a></span>‘Look! The days are coming,’ declares Jehovah,</p><p class='sz'><span class='br'></span>‘When the plowman will overtake the harvester,</p><p class='sz'><span class='br'></span>And the treader of grapes, the one carrying seed;<a class='mr'></a></p><p class='sz'><span class='br'></span>And the mountains will drip with sweet wine,<a class='mr'></a></p><p class='sz'><span class='br'></span>And all the hills will flow with it.<a class='fn'></a><a class='mr'></a></p></div><div id='p166' class='par'><p class='sl'><span id='dcv_9_14' class='dv dx dp'><a>14 </a></span>I will gather back the captives of my people Israel,<a class='mr'></a></p><p class='sz'><span class='br'></span>And they will rebuild the desolated cities and inhabit them;<a class='mr'></a></p><p class='sz'><span class='br'></span>They will plant vineyards and drink their wine,<a class='mr'></a></p><p class='sz'><span class='br'></span>And make gardens and eat their fruit.’<a class='mr'></a></p></div><div id='p167' class='par'><p class='sl'><span id='dcv_9_15' class='dv dx dp'><a>15 </a></span>‘I will plant them on their land,</p><p class='sz'><span class='br'></span>And they will never again be uprooted</p><p class='sz'><span class='br'></span>From their land that I have given them,’<a class='mr'></a> says Jehovah your God.”</p></div></div></text>
</bible>
